DataRestriction/BaseProperties.py
DataRestriction/DerivedProperties.py
DataRestriction/ErrorMessages.py
DataRestriction/__init__.py
Debug/debug.py
datarestriction-0.15.0.dist-info/licenses/LICENSE
datarestriction-0.15.0.dist-info/METADATA
datarestriction-0.15.0.dist-info/WHEEL
datarestriction-0.15.0.dist-info/top_level.txt
datarestriction-0.15.0.dist-info/RECORD
