Metadata-Version: 2.4
Name: DataRestriction
Version: 0.15.0
Summary: A package for restricting the data type of user input
Author-email: luomeng007 <1502506285@qq.com>
Project-URL: Homepage, https://gitee.com/camarolm/DataRestriction
Project-URL: Bug Tracker, https://gitee.com/camarolm/DataRestriction/issues
Classifier: Development Status :: 5 - Production/Stable
Classifier: Programming Language :: Python :: 3
Classifier: License :: OSI Approved :: GNU General Public License v3 (GPLv3)
Classifier: Topic :: Software Development :: Libraries
Classifier: Operating System :: OS Independent
Requires-Python: >=3.7
License-File: LICENSE
Requires-Dist: Numpy>=2.0.0
Dynamic: license-file
